[
  {
    "dups": {
      "67009": 2
    },
    "service": "372",
    "route": 1
  },
  {
    "dups": {
      "53009": 2
    },
    "service": "410G",
    "route": 1
  },
  {
    "dups": {
      "66009": 2,
      "66271": 2
    },
    "service": "315",
    "route": 1
  },
  {
    "dups": {
      "10589": 2
    },
    "service": "120",
    "route": 1
  },
  {
    "dups": {
      "82009": 2
    },
    "service": "63M",
    "route": 1
  },
  {
    "dups": {
      "03239": 2
    },
    "service": "402",
    "route": 1
  },
  {
    "dups": {
      "52009": 2
    },
    "service": "238",
    "route": 1
  },
  {
    "dups": {
      "46009": 2
    },
    "service": "964",
    "route": 1
  },
  {
    "dups": {
      "75009": 3
    },
    "service": "291",
    "route": 1
  },
  {
    "dups": {
      "59009": 2
    },
    "service": "812",
    "route": 1
  },
  {
    "dups": {
      "66009": 2
    },
    "service": "158",
    "route": 1
  },
  {
    "dups": {
      "64009": 2
    },
    "service": "113",
    "route": 1
  },
  {
    "dups": {
      "59009": 2
    },
    "service": "806",
    "route": 1
  },
  {
    "dups": {
      "84009": 2
    },
    "service": "225W",
    "route": 1
  },
  {
    "dups": {
      "44009": 2
    },
    "service": "302",
    "route": 1
  },
  {
    "dups": {
      "25009": 2
    },
    "service": "247",
    "route": 1
  },
  {
    "dups": {
      "24009": 2
    },
    "service": "255",
    "route": 1
  },
  {
    "dups": {
      "44009": 2
    },
    "service": "301",
    "route": 1
  },
  {
    "dups": {
      "52129": 2,
      "52499": 2,
      "52109": 2
    },
    "service": "125",
    "route": 1
  },
  {
    "dups": {
      "65009": 2
    },
    "service": "119",
    "route": 1
  },
  {
    "dups": {
      "22009": 2
    },
    "service": "180",
    "route": 1
  },
  {
    "dups": {
      "75009": 2
    },
    "service": "37",
    "route": 1
  },
  {
    "dups": {
      "10589": 2
    },
    "service": "121",
    "route": 1
  },
  {
    "dups": {
      "22009": 2
    },
    "service": "181M",
    "route": 1
  },
  {
    "dups": {
      "64009": 2
    },
    "service": "107M",
    "route": 1
  },
  {
    "dups": {
      "54009": 2
    },
    "service": "265",
    "route": 1
  },
  {
    "dups": {
      "82009": 2
    },
    "service": "94",
    "route": 1
  },
  {
    "dups": {
      "52009": 2
    },
    "service": "139M",
    "route": 1
  },
  {
    "dups": {
      "54009": 2
    },
    "service": "261",
    "route": 1
  },
  {
    "dups": {
      "44009": 2
    },
    "service": "307",
    "route": 1
  },
  {
    "dups": {
      "10009": 2
    },
    "service": "273",
    "route": 1
  },
  {
    "dups": {
      "22009": 2
    },
    "service": "181",
    "route": 1
  },
  {
    "dups": {
      "03239": 2
    },
    "service": "400",
    "route": 1
  },
  {
    "dups": {
      "65009": 2
    },
    "service": "83",
    "route": 1
  },
  {
    "dups": {
      "54009": 2
    },
    "service": "24",
    "route": 1
  },
  {
    "dups": {
      "80199": 2,
      "80191": 2,
      "80009": 2
    },
    "service": "11",
    "route": 1
  },
  {
    "dups": {
      "24009": 2
    },
    "service": "254",
    "route": 1
  },
  {
    "dups": {
      "46009": 2
    },
    "service": "900A",
    "route": 1
  },
  {
    "dups": {
      "17009": 2
    },
    "service": "285",
    "route": 1
  },
  {
    "dups": {
      "52009": 2
    },
    "service": "142",
    "route": 1
  },
  {
    "dups": {
      "64009": 2
    },
    "service": "112",
    "route": 1
  },
  {
    "dups": {
      "22009": 2
    },
    "service": "179",
    "route": 1
  },
  {
    "dups": {
      "43009": 2,
      "43719": 2
    },
    "service": "177",
    "route": 1
  },
  {
    "dups": {
      "77009": 2
    },
    "service": "15",
    "route": 1
  },
  {
    "dups": {
      "54009": 2
    },
    "service": "265A",
    "route": 1
  },
  {
    "dups": {
      "75009": 3
    },
    "service": "293",
    "route": 1
  },
  {
    "dups": {
      "22009": 2
    },
    "service": "194",
    "route": 1
  },
  {
    "dups": {
      "54009": 2,
      "66271": 2
    },
    "service": "73",
    "route": 1
  },
  {
    "dups": {
      "58009": 2
    },
    "service": "859A",
    "route": 1
  },
  {
    "dups": {
      "55009": 2
    },
    "service": "268",
    "route": 1
  },
  {
    "dups": {
      "53371": 2,
      "53049": 2,
      "53409": 2,
      "53331": 2,
      "53009": 4,
      "53281": 2,
      "53341": 2,
      "53069": 2,
      "53321": 2,
      "53129": 2,
      "53381": 2,
      "53351": 2,
      "53261": 2,
      "53299": 2,
      "53319": 2,
      "53059": 2,
      "53309": 2,
      "53391": 2,
      "53271": 2,
      "53419": 2,
      "53361": 2
    },
    "service": "410",
    "route": 1
  },
  {
    "dups": {
      "53401": 2,
      "53339": 2,
      "53279": 2,
      "53121": 2,
      "53399": 2,
      "53369": 2,
      "53301": 2,
      "53379": 2,
      "53329": 2,
      "53289": 2,
      "53051": 2,
      "53291": 2,
      "53221": 2,
      "53009": 4,
      "53061": 2,
      "53389": 2,
      "53269": 2,
      "53041": 2,
      "53179": 2,
      "53311": 2,
      "53359": 2,
      "53349": 2
    },
    "service": "410",
    "route": 2
  },
  {
    "dups": {
      "84009": 2
    },
    "service": "35M",
    "route": 1
  },
  {
    "dups": {
      "65009": 2
    },
    "service": "386",
    "route": 1
  },
  {
    "dups": {
      "65009": 2
    },
    "service": "34",
    "route": 1
  },
  {
    "dups": {
      "22609": 2
    },
    "service": "502",
    "route": 1
  },
  {
    "dups": {
      "44009": 2
    },
    "service": "300",
    "route": 1
  },
  {
    "dups": {
      "59009": 2
    },
    "service": "804",
    "route": 1
  },
  {
    "dups": {
      "28009": 2
    },
    "service": "183",
    "route": 1
  },
  {
    "dups": {
      "64009": 2
    },
    "service": "329",
    "route": 1
  },
  {
    "dups": {
      "53009": 2
    },
    "service": "53",
    "route": 1
  },
  {
    "dups": {
      "82009": 2
    },
    "service": "150",
    "route": 1
  },
  {
    "dups": {
      "46009": 2
    },
    "service": "950",
    "route": 1
  },
  {
    "dups": {
      "59009": 2
    },
    "service": "800",
    "route": 1
  },
  {
    "dups": {
      "75009": 2
    },
    "service": "292",
    "route": 1
  },
  {
    "dups": {
      "84009": 2
    },
    "service": "40",
    "route": 1
  },
  {
    "dups": {
      "24009": 2
    },
    "service": "257",
    "route": 1
  },
  {
    "dups": {
      "46009": 2
    },
    "service": "965",
    "route": 1
  },
  {
    "dups": {
      "54009": 2
    },
    "service": "138",
    "route": 1
  },
  {
    "dups": {
      "64009": 2
    },
    "service": "324",
    "route": 1
  },
  {
    "dups": {
      "43009": 2
    },
    "service": "173",
    "route": 1
  },
  {
    "dups": {
      "46009": 2
    },
    "service": "911",
    "route": 1
  },
  {
    "dups": {
      "25009": 2
    },
    "service": "248",
    "route": 1
  },
  {
    "dups": {
      "11009": 2
    },
    "service": "92M",
    "route": 1
  },
  {
    "dups": {
      "22009": 2
    },
    "service": "240",
    "route": 1
  },
  {
    "dups": {
      "82009": 2,
      "84501": 2,
      "84511": 2
    },
    "service": "60",
    "route": 1
  },
  {
    "dups": {
      "22009": 2
    },
    "service": "249",
    "route": 1
  },
  {
    "dups": {
      "77009": 3
    },
    "service": "359",
    "route": 1
  },
  {
    "dups": {
      "63221": 2
    },
    "service": "115",
    "route": 1
  },
  {
    "dups": {
      "55509": 2
    },
    "service": "162M",
    "route": 1
  },
  {
    "dups": {
      "65009": 2
    },
    "service": "381",
    "route": 1
  },
  {
    "dups": {
      "14381": 2,
      "14389": 2,
      "14009": 2
    },
    "service": "123M",
    "route": 1
  },
  {
    "dups": {
      "65009": 2
    },
    "service": "382G",
    "route": 1
  },
  {
    "dups": {
      "46009": 2
    },
    "service": "925C",
    "route": 1
  },
  {
    "dups": {
      "65009": 2
    },
    "service": "84",
    "route": 1
  },
  {
    "dups": {
      "52009": 2
    },
    "service": "232",
    "route": 1
  },
  {
    "dups": {
      "58009": 2
    },
    "service": "859",
    "route": 1
  },
  {
    "dups": {
      "28009": 2
    },
    "service": "335",
    "route": 1
  },
  {
    "dups": {
      "21089": 2,
      "21069": 2,
      "21079": 2,
      "21109": 2,
      "28009": 2
    },
    "service": "98",
    "route": 1
  },
  {
    "dups": {
      "54009": 2
    },
    "service": "135",
    "route": 1
  },
  {
    "dups": {
      "75009": 2
    },
    "service": "69",
    "route": 1
  },
  {
    "dups": {
      "67009": 2
    },
    "service": "163M",
    "route": 1
  },
  {
    "dups": {
      "43009": 2
    },
    "service": "945",
    "route": 1
  },
  {
    "dups": {
      "46009": 2
    },
    "service": "962",
    "route": 1
  },
  {
    "dups": {
      "58009": 2
    },
    "service": "882",
    "route": 1
  },
  {
    "dups": {
      "84009": 2
    },
    "service": "229",
    "route": 1
  },
  {
    "dups": {
      "22009": 2
    },
    "service": "252",
    "route": 1
  },
  {
    "dups": {
      "66009": 2
    },
    "service": "101",
    "route": 1
  },
  {
    "dups": {
      "75009": 2
    },
    "service": "20",
    "route": 1
  },
  {
    "dups": {
      "58009": 2
    },
    "service": "859B",
    "route": 1
  },
  {
    "dups": {
      "83321": 2
    },
    "service": "42",
    "route": 1
  },
  {
    "dups": {
      "59009": 2
    },
    "service": "860",
    "route": 1
  },
  {
    "dups": {
      "46009": 2
    },
    "service": "903M",
    "route": 1
  },
  {
    "dups": {
      "65009": 2
    },
    "service": "43M",
    "route": 1
  },
  {
    "dups": {
      "59009": 2
    },
    "service": "803",
    "route": 1
  },
  {
    "dups": {
      "44009": 2
    },
    "service": "927",
    "route": 1
  },
  {
    "dups": {
      "46009": 2
    },
    "service": "901",
    "route": 1
  },
  {
    "dups": {
      "84009": 2,
      "96219": 2
    },
    "service": "35",
    "route": 1
  },
  {
    "dups": {
      "43009": 2
    },
    "service": "189",
    "route": 1
  },
  {
    "dups": {
      "59009": 2
    },
    "service": "857",
    "route": 1
  },
  {
    "dups": {
      "53009": 2
    },
    "service": "410W",
    "route": 1
  },
  {
    "dups": {
      "80289": 2
    },
    "service": "134",
    "route": 1
  },
  {
    "dups": {
      "75019": 2
    },
    "service": "18",
    "route": 1
  },
  {
    "dups": {
      "55509": 2
    },
    "service": "529",
    "route": 1
  },
  {
    "dups": {
      "22009": 2
    },
    "service": "243W",
    "route": 1
  },
  {
    "dups": {
      "24009": 2
    },
    "service": "253",
    "route": 1
  },
  {
    "dups": {
      "75009": 2
    },
    "service": "81",
    "route": 1
  },
  {
    "dups": {
      "28009": 2
    },
    "service": "79",
    "route": 1
  },
  {
    "dups": {
      "22009": 2
    },
    "service": "243G",
    "route": 1
  },
  {
    "dups": {
      "24009": 2
    },
    "service": "258",
    "route": 1
  },
  {
    "dups": {
      "46009": 2
    },
    "service": "903",
    "route": 1
  },
  {
    "dups": {
      "22009": 2
    },
    "service": "242",
    "route": 1
  },
  {
    "dups": {
      "75009": 2
    },
    "service": "4",
    "route": 1
  },
  {
    "dups": {
      "43009": 2
    },
    "service": "941",
    "route": 1
  },
  {
    "dups": {
      "75009": 2
    },
    "service": "29",
    "route": 1
  },
  {
    "dups": {
      "16009": 2
    },
    "service": "95",
    "route": 1
  },
  {
    "dups": {
      "28009": 2
    },
    "service": "160",
    "route": 1
  },
  {
    "dups": {
      "28009": 2
    },
    "service": "41",
    "route": 1
  },
  {
    "dups": {
      "22009": 2
    },
    "service": "251",
    "route": 1
  },
  {
    "dups": {
      "84009": 2
    },
    "service": "222",
    "route": 1
  },
  {
    "dups": {
      "75009": 2
    },
    "service": "23",
    "route": 1
  },
  {
    "dups": {
      "67759": 2
    },
    "service": "374",
    "route": 1
  },
  {
    "dups": {
      "65009": 2
    },
    "service": "382W",
    "route": 1
  },
  {
    "dups": {
      "84009": 2
    },
    "service": "225G",
    "route": 1
  },
  {
    "dups": {
      "65009": 2
    },
    "service": "62",
    "route": 1
  },
  {
    "dups": {
      "22009": 2
    },
    "service": "246",
    "route": 1
  },
  {
    "dups": {
      "77009": 2
    },
    "service": "518",
    "route": 1
  },
  {
    "dups": {
      "52009": 2
    },
    "service": "90",
    "route": 1
  },
  {
    "dups": {
      "84009": 2
    },
    "service": "401",
    "route": 1
  },
  {
    "dups": {
      "64009": 2
    },
    "service": "89",
    "route": 1
  },
  {
    "dups": {
      "77009": 2
    },
    "service": "6",
    "route": 1
  },
  {
    "dups": {
      "67009": 2
    },
    "service": "371",
    "route": 1
  },
  {
    "dups": {
      "11009": 2
    },
    "service": "111",
    "route": 1
  },
  {
    "dups": {
      "84009": 2
    },
    "service": "225",
    "route": 1
  },
  {
    "dups": {
      "84009": 2
    },
    "service": "225",
    "route": 2
  },
  {
    "dups": {
      "75009": 2
    },
    "service": "19",
    "route": 1
  },
  {
    "dups": {
      "46009": 2
    },
    "service": "913",
    "route": 1
  },
  {
    "dups": {
      "46009": 2
    },
    "service": "926",
    "route": 1
  },
  {
    "dups": {
      "59009": 2
    },
    "service": "805",
    "route": 1
  },
  {
    "dups": {
      "11379": 2
    },
    "service": "191",
    "route": 1
  },
  {
    "dups": {
      "22009": 2
    },
    "service": "199",
    "route": 1
  },
  {
    "dups": {
      "59009": 2
    },
    "service": "811",
    "route": 1
  },
  {
    "dups": {
      "43009": 2
    },
    "service": "990",
    "route": 1
  },
  {
    "dups": {
      "52009": 2
    },
    "service": "231",
    "route": 1
  },
  {
    "dups": {
      "54009": 2
    },
    "service": "262",
    "route": 1
  },
  {
    "dups": {
      "58009": 2
    },
    "service": "883",
    "route": 1
  },
  {
    "dups": {
      "84009": 2
    },
    "service": "228",
    "route": 1
  },
  {
    "dups": {
      "46009": 2
    },
    "service": "858",
    "route": 1
  },
  {
    "dups": {
      "10589": 2
    },
    "service": "122",
    "route": 1
  },
  {
    "dups": {
      "82009": 2
    },
    "service": "63",
    "route": 1
  },
  {
    "dups": {
      "28009": 2
    },
    "service": "334",
    "route": 1
  },
  {
    "dups": {
      "44009": 2
    },
    "service": "308",
    "route": 1
  },
  {
    "dups": {
      "28009": 2
    },
    "service": "49",
    "route": 1
  },
  {
    "dups": {
      "65009": 2
    },
    "service": "82",
    "route": 1
  },
  {
    "dups": {
      "95129": 2
    },
    "service": "36",
    "route": 1
  },
  {
    "dups": {
      "77009": 2
    },
    "service": "403",
    "route": 1
  },
  {
    "dups": {
      "46009": 2
    },
    "service": "966",
    "route": 1
  },
  {
    "dups": {
      "64009": 2
    },
    "service": "102",
    "route": 1
  },
  {
    "dups": {
      "24009": 2
    },
    "service": "182M",
    "route": 1
  },
  {
    "dups": {
      "10009": 2
    },
    "service": "131M",
    "route": 1
  },
  {
    "dups": {
      "28009": 2
    },
    "service": "78",
    "route": 1
  },
  {
    "dups": {
      "22009": 2
    },
    "service": "405",
    "route": 1
  },
  {
    "dups": {
      "10009": 2
    },
    "service": "272",
    "route": 1
  },
  {
    "dups": {
      "25269": 2,
      "24009": 2
    },
    "service": "182",
    "route": 1
  },
  {
    "dups": {
      "52009": 2
    },
    "service": "235",
    "route": 1
  },
  {
    "dups": {
      "55509": 2
    },
    "service": "70M",
    "route": 1
  },
  {
    "dups": {
      "80289": 2
    },
    "service": "64",
    "route": 1
  },
  {
    "dups": {
      "46009": 2
    },
    "service": "904",
    "route": 1
  },
  {
    "dups": {
      "77009": 2
    },
    "service": "354",
    "route": 1
  },
  {
    "dups": {
      "28009": 2
    },
    "service": "333",
    "route": 1
  },
  {
    "dups": {
      "64009": 2
    },
    "service": "27",
    "route": 1
  },
  {
    "dups": {
      "55509": 2
    },
    "service": "825",
    "route": 1
  },
  {
    "dups": {
      "45009": 2
    },
    "service": "922",
    "route": 1
  },
  {
    "dups": {
      "28009": 2
    },
    "service": "143M",
    "route": 1
  },
  {
    "dups": {
      "17009": 2
    },
    "service": "96",
    "route": 1
  },
  {
    "dups": {
      "64009": 2
    },
    "service": "116",
    "route": 1
  },
  {
    "dups": {
      "11009": 2
    },
    "service": "92",
    "route": 1
  },
  {
    "dups": {
      "80009": 2
    },
    "service": "140",
    "route": 1
  },
  {
    "dups": {
      "64009": 2
    },
    "service": "325",
    "route": 1
  },
  {
    "dups": {
      "22009": 2
    },
    "service": "241",
    "route": 1
  },
  {
    "dups": {
      "16009": 2
    },
    "service": "201",
    "route": 1
  },
  {
    "dups": {
      "97009": 2
    },
    "service": "47",
    "route": 1
  },
  {
    "dups": {
      "84009": 2
    },
    "service": "9",
    "route": 1
  },
  {
    "dups": {
      "28009": 2
    },
    "service": "98M",
    "route": 1
  },
  {
    "dups": {
      "17009": 2
    },
    "service": "282",
    "route": 1
  },
  {
    "dups": {
      "66009": 2,
      "66271": 2
    },
    "service": "317",
    "route": 1
  },
  {
    "dups": {
      "46009": 2
    },
    "service": "912",
    "route": 1
  },
  {
    "dups": {
      "54009": 2
    },
    "service": "269",
    "route": 1
  },
  {
    "dups": {
      "44009": 2
    },
    "service": "983",
    "route": 1
  },
  {
    "dups": {
      "46009": 2
    },
    "service": "900",
    "route": 1
  },
  {
    "dups": {
      "77009": 3
    },
    "service": "358",
    "route": 1
  },
  {
    "dups": {
      "22009": 2
    },
    "service": "243",
    "route": 1
  },
  {
    "dups": {
      "22009": 2
    },
    "service": "243",
    "route": 2
  },
  {
    "dups": {
      "43009": 2
    },
    "service": "947",
    "route": 1
  },
  {
    "dups": {
      "17009": 2
    },
    "service": "284",
    "route": 1
  },
  {
    "dups": {
      "75009": 2
    },
    "service": "127",
    "route": 1
  }
]